[{"model": "events.event", "pk": 2, "fields": {"title": "Churras na casa do Tiago", "description": "Open caipirosca e picanha", "start_date": "2018-05-17", "kind": 1}}, {"model": "events.event", "pk": 3, "fields": {"title": "Caf\u00e9 da manh\u00e3 na casa do ronaldo", "description": "open de tody", "start_date": "2018-05-18", "kind": 1}}, {"model": "events.event", "pk": 4, "fields": {"title": "Evento Extens\u00e3o 1", "description": "Evento Extens\u00e3o 1", "start_date": "2018-05-24", "kind": 3}}, {"model": "events.event", "pk": 5, "fields": {"title": "Evento Extens\u00e3o 1", "description": "Evento Extens\u00e3o 1", "start_date": "2018-05-24", "kind": 3}}, {"model": "events.event", "pk": 6, "fields": {"title": "Evento Ensino 1", "description": "Evento Ensino 1", "start_date": "2018-05-24", "kind": 2}}, {"model": "events.event", "pk": 7, "fields": {"title": "Evento Ensino 1", "description": "Desc Ensino", "start_date": "2018-05-24", "kind": 2}}, {"model": "events.registration", "pk": 1, "fields": {"event": 6, "user": 2, "status": 1}}]